README.md
license.txt
setup.cfg
setup.py
src/book/__init__.py
src/teocomp/__init__.py
src/teocomp/bcolors.py
src/teocomp/decoder_automaton.py
src/teocomp/dfa.py
src/teocomp/encoder_lu2pcpm.py
src/teocomp/fr_kleene.py
src/teocomp/mt.py
src/teocomp/mt_encoder.py
src/teocomp/mt_exercicio.py
src/teocomp/mt_mf.py
src/teocomp/mt_nd.py
src/teocomp/mt_ndmf.py
src/teocomp/nfa.py
src/teocomp/nfa_bb.py
src/teocomp/nfa_e.py
src/teocomp/pcp.py
src/teocomp/pcp_exercicio.py
src/teocomp/pcpm.py
src/teocomp/sets_relations_languages.py
src/teocomp.egg-info/PKG-INFO
src/teocomp.egg-info/SOURCES.txt
src/teocomp.egg-info/dependency_links.txt
src/teocomp.egg-info/requires.txt
src/teocomp.egg-info/top_level.txt